LICENSE
MANIFEST.in
README.rst
requirements-dev.txt
requirements-test.txt
requirements.txt
setup.cfg
setup.py
tox.ini
docs/Makefile
docs/source/conf.py
docs/source/index.rst
docs/source/linebot.models.rst
docs/source/linebot.rst
line_bot_sdk567894.egg-info/PKG-INFO
line_bot_sdk567894.egg-info/SOURCES.txt
line_bot_sdk567894.egg-info/dependency_links.txt
line_bot_sdk567894.egg-info/requires.txt
line_bot_sdk567894.egg-info/top_level.txt
linebot77/__about__.py
linebot77/__init__.py
linebot77/api.py
linebot77/exceptions.py
linebot77/http_client.py
linebot77/utils.py
linebot77/webhook.py
linebot77/models/__init__.py
linebot77/models/base.py
linebot77/models/error.py
linebot77/models/events.py
linebot77/models/imagemap.py
linebot77/models/messages.py
linebot77/models/responses.py
linebot77/models/send_messages.py
linebot77/models/sources.py
linebot77/models/template.py
tests/__init__.py
tests/test_utils.py
tests/test_webhook.py
tests/api/__init__.py
tests/api/test_error_handle.py
tests/api/test_get_content.py
tests/api/test_get_member_ids.py
tests/api/test_get_member_profile.py
tests/api/test_get_profile.py
tests/api/test_leave.py
tests/api/test_send_audio_message.py
tests/api/test_send_image_message.py
tests/api/test_send_imagemap_message.py
tests/api/test_send_location_message.py
tests/api/test_send_sticker_message.py
tests/api/test_send_template_message.py
tests/api/test_send_text_message.py
tests/api/test_send_video_message.py
tests/models/__init__.py
tests/models/test_base.py
tests/text/webhook.json